pytest_slack/__init__.py
pytest_slack/plugin.py
pytest_slack-2.3.1.dist-info/AUTHORS.rst
pytest_slack-2.3.1.dist-info/LICENSE
pytest_slack-2.3.1.dist-info/METADATA
pytest_slack-2.3.1.dist-info/WHEEL
pytest_slack-2.3.1.dist-info/entry_points.txt
pytest_slack-2.3.1.dist-info/top_level.txt
pytest_slack-2.3.1.dist-info/RECORD
