Metadata-Version: 1.1
Name: pytest-slack
Version: 2.3.1
Summary: Pytest to Slack reporting plugin
Home-page: https://github.com/pytest-dev/pytest-slack
Author: LaserPhaser
Author-email: arseny.antonov@gmail.com
License: MIT license
Keywords: pytest,py.test,slack
Platform: UNKNOWN
Classifier: Framework :: Pytest
Classifier: Development Status :: 5 - Production/Stable
Classifier: Intended Audience :: Developers
Classifier: License :: OSI Approved :: MIT License
Classifier: Natural Language :: English
Classifier: Programming Language :: Python :: 2.7
Classifier: Programming Language :: Python :: 3.6
Classifier: Programming Language :: Python :: 3.7
Classifier: Programming Language :: Python :: 3.8
